[{"my_id":0,"name":"bed","state":{"selected":false,"checked":true},"text":"Bed","nodes":[{"my_id":1,"name":"regular_bed","state":{"selected":false,"checked":true},"text":"Regular bed","nodes":[{"my_id":2,"name":"bed_unit","state":{"selected":false,"checked":true},"text":"Bed Unit","nodes":[{"my_id":3,"name":"bed_sleep_area","icon":"glyphicon glyphicon-question-sign","state":{"selected":false,"checked":true},"text":"Bed sleep area"},{"my_id":4,"name":"bed_frame","state":{"selected":false,"checked":true},"text":"Bed frame","nodes":[{"my_id":5,"name":"headboard","icon":"glyphicon glyphicon-question-sign","state":{"selected":false,"checked":true},"text":"Headboard"},{"my_id":6,"name":"bed_frame_horizontal_surface","state":{"selected":false,"checked":true},"text":"Bed frame horizontal surface","nodes":[{"my_id":7,"name":"frame_horizontal_hard_surface","state":{"selected":false,"checked":true},"text":"Frame horizontal hard surface","parts":["original-29"],"color":"#5af3d4"}]}]}]}]}]}]